[
  {
    "candidate_id": "e69cbdf7fe80efcb5c4c4f53e45c51cd35bbb23cf128d41cfdcb55d8369cc8b4",
    "full_name": "Nikita Gupta",
    "emails": [
      "nikitagpt06@gmail.com"
    ],
    "phones": [
      "+919818134486"
    ],
    "location": null,
    "links": null,
    "headline": null,
    "years_experience": null,
    "skills": [
      {
        "name": "Python",
        "confidence": 0.95,
        "sources": [
          "csv"
        ]
      },
      {
        "name": "Machine Learning",
        "confidence": 0.95,
        "sources": [
          "csv"
        ]
      },
      {
        "name": "JavaScript",
        "confidence": 0.75,
        "sources": [
          "resume:resume.txt"
        ]
      },
      {
        "name": "Node.js",
        "confidence": 0.75,
        "sources": [
          "resume:resume.txt"
        ]
      }
    ],
    "experience": [
      {
        "company": "Google",
        "title": "Software Engineer",
        "start": null,
        "end": null,
        "summary": null
      }
    ],
    "education": [],
    "overall_confidence": 0.9056,
    "provenance": [
      {
        "field": "full_name",
        "source": "csv",
        "method": "csv_column"
      },
      {
        "field": "experience[0].company",
        "source": "csv",
        "method": "csv_column"
      },
      {
        "field": "experience[0].title",
        "source": "csv",
        "method": "csv_column"
      },
      {
        "field": "emails[0]",
        "source": "csv",
        "method": "csv_column"
      },
      {
        "field": "phones[0]",
        "source": "csv",
        "method": "csv_column"
      },
      {
        "field": "skills[0]",
        "sources": [
          "csv"
        ],
        "method": "extracted"
      },
      {
        "field": "skills[1]",
        "sources": [
          "csv"
        ],
        "method": "extracted"
      },
      {
        "field": "skills[2]",
        "sources": [
          "resume:resume.txt"
        ],
        "method": "extracted"
      },
      {
        "field": "skills[3]",
        "sources": [
          "resume:resume.txt"
        ],
        "method": "extracted"
      }
    ]
  },
  {
    "candidate_id": "7872f5192ca7ca8e8c868ab58289f25028c8a626d74ab02c0e5a4dd725ef9102",
    "full_name": "Manav Garg",
    "emails": [
      "manavgarg2209@gmail.com"
    ],
    "phones": [
      "+918630029486"
    ],
    "location": null,
    "links": null,
    "headline": null,
    "years_experience": null,
    "skills": [
      {
        "name": "Java",
        "confidence": 0.95,
        "sources": [
          "csv"
        ]
      },
      {
        "name": "JavaScript",
        "confidence": 0.95,
        "sources": [
          "csv"
        ]
      }
    ],
    "experience": [
      {
        "company": "Amazon",
        "title": "Backend Eng",
        "start": null,
        "end": null,
        "summary": null
      }
    ],
    "education": [],
    "overall_confidence": 0.95,
    "provenance": [
      {
        "field": "full_name",
        "source": "csv",
        "method": "csv_column"
      },
      {
        "field": "experience[0].company",
        "source": "csv",
        "method": "csv_column"
      },
      {
        "field": "experience[0].title",
        "source": "csv",
        "method": "csv_column"
      },
      {
        "field": "emails[0]",
        "source": "csv",
        "method": "csv_column"
      },
      {
        "field": "phones[0]",
        "source": "csv",
        "method": "csv_column"
      },
      {
        "field": "skills[0]",
        "sources": [
          "csv"
        ],
        "method": "extracted"
      },
      {
        "field": "skills[1]",
        "sources": [
          "csv"
        ],
        "method": "extracted"
      }
    ]
  }
]